silence_lint_error/__init__.py
silence_lint_error/comments.py
silence_lint_error/fixing.py
silence_lint_error/silencing.py
silence_lint_error/cli/__init__.py
silence_lint_error/cli/config.py
silence_lint_error/cli/fix_silenced_error.py
silence_lint_error/cli/silence_lint_error.py
silence_lint_error/linters/__init__.py
silence_lint_error/linters/fixit.py
silence_lint_error/linters/flake8.py
silence_lint_error/linters/mypy.py
silence_lint_error/linters/ruff.py
silence_lint_error/linters/semgrep.py
silence_lint_error-1.7.0.dist-info/licenses/LICENSE
silence_lint_error-1.7.0.dist-info/METADATA
silence_lint_error-1.7.0.dist-info/WHEEL
silence_lint_error-1.7.0.dist-info/entry_points.txt
silence_lint_error-1.7.0.dist-info/top_level.txt
silence_lint_error-1.7.0.dist-info/RECORD
