Metadata-Version: 2.4
Name: silence_lint_error
Version: 1.7.0
Summary: silence linting errors by adding ignore/fixme comments
Author-email: Samuel Searles-Bryant <sam@samueljsb.co.uk>
License-Expression: MIT
Project-URL: Source, https://github.com/samueljsb/silence-lint-error
Project-URL: Changelog, https://github.com/samueljsb/silence-lint-error/blob/main/CHANGELOG.md
Classifier: Programming Language :: Python :: 3 :: Only
Classifier: Programming Language :: Python :: 3
Classifier: Programming Language :: Python :: 3.9
Classifier: Programming Language :: Python :: 3.10
Classifier: Programming Language :: Python :: 3.11
Classifier: Programming Language :: Python :: 3.12
Classifier: Programming Language :: Python :: 3.13
Requires-Python: >=3.9
License-File: LICENSE
Requires-Dist: attrs
Requires-Dist: tokenize-rt
Dynamic: license-file
